{
  "iati_identifier": "GB-CHC-1001813-UKAidMatchZimbabwe",
  "reporting_org": "GB-CHC-1001813",
  "reporting_org_type": "21",
  "title": "UKAM: New technology to accelerate landmine removal for Zimbabwe's rural poor October 2020 to September 2021",
  "description": "This project aims to safe lives and increase livelihoods in Zimbabwe by: 1) clearing landmines, and 2) providing risk education",
  "default_currency": "USD",
  "default_flow_type": "UNKNOWN",
  "default_aid_type": "B01",
  "default_finance_type": "110",
  "default_tied_status": null,
  "transactions": []
}