{
  "iati_identifier": "KR-GOV-010-KR-GOV-051-2021010100038",
  "reporting_org": "KR-GOV-010",
  "reporting_org_type": "10",
  "title": "Mine Action for Human Development Program in Cambodia (Clearing for Results IV)",
  "description": "the clearance of an additional 56km2 of mine affected land, the people living in the 125 targe villages",
  "default_currency": "USD",
  "default_flow_type": "10",
  "default_aid_type": "C01",
  "default_finance_type": "110",
  "default_tied_status": "5",
  "transactions": [
    {
      "value": 12100000000.0,
      "date": "2021-01-01T00:00:00Z",
      "type": "1",
      "sector": null,
      "sector_vocabularly": null,
      "recipient_country": null,
      "recipient_region": null
    },
    {
      "value": 0.0,
      "date": "2021-03-15T00:00:00Z",
      "type": "2",
      "sector": null,
      "sector_vocabularly": null,
      "recipient_country": null,
      "recipient_region": null
    },
    {
      "value": 2292178381.0,
      "date": "2024-12-31T00:00:00Z",
      "type": "3",
      "sector": null,
      "sector_vocabularly": null,
      "recipient_country": null,
      "recipient_region": null
    }
  ]
}